[
  {
    "id": 1,
    "value": "multiple_choice",
    "type_question": {
      "name": "Choix multiples",
      "slug": "multiple_choice"
    },
    "response_options": [
      {
        "correct_answer": false,
        "name": "option 1",
        "poids": null,
        "points": 0,
        "slug": "option1",
        "action": {}
      }
    ],
    "is_mandatory": false,
    "response_redirection": false,
    "question_is_selected": "",

    "activate_vote": false,
    "constraint": "",
    "correction_explanation": "",
    "placeholder": "",
    "poids": "",
    "with_validation_contrainte": false,
    "corection": false
  },
  {
    "id": 2,
    "value": "checkboxes",
    "type_question": {
      "name": "Cases à cocher",
      "slug": "checkbox"
    },
    "response_options": [
      {
        "correct_answer": false,
        "name": "option 1",
        "poids": null,
        "points": 0,
        "slug": "option1",
        "action": {}
      }
    ],
    "is_mandatory": false,
    "response_redirection": false,
    "question_is_selected": "",

    "activate_vote": false,
    "constraint": "",
    "correction_explanation": "",
    "description": "",
    "placeholder": "",
    "poids": "",
    "with_validation_contrainte": false,
    "corection": false
  },
  {
    "id": 3,
    "value": "short_answer",
    "type_question": {
      "name": "Réponse courte",
      "slug": "short_answer"
    },
    "response_options": [],
    "is_mandatory": false,
    "response_redirection": false,
    "question_is_selected": "",

    "activate_vote": false,
    "constraint": {},
    "correction_explanation": "",
    "description": "",
    "placeholder": "",
    "poids": "",
    "with_validation_contrainte": false,
    "corection": false
  },
  {
    "id": 4,
    "value": "long_answer",
    "type_question": {
      "name": "Réponse longue",
      "slug": "width_answer"
    },
    "response_options": [],
    "is_mandatory": false,
    "response_redirection": false,
    "question_is_selected": "",

    "activate_vote": false,
    "constraint": {},
    "correction_explanation": "",
    "description": "",
    "placeholder": "",
    "poids": "",
    "with_validation_contrainte": false,
    "corection": false
  },
  {
    "id": 5,
    "value": "select",
    "type_question": {
      "name": "Liste déroulante",
      "slug": "list_scroll"
    },
    "response_options": [
      {
        "correct_answer": false,
        "name": "option 1",
        "poids": null,
        "points": 0,
        "slug": "option1",
        "action": {}
      }
    ],
    "is_mandatory": false,
    "response_redirection": false,
    "question_is_selected": "",

    "activate_vote": false,
    "constraint": "",
    "correction_explanation": "",
    "description": "",
    "placeholder": "",
    "poids": "",
    "with_validation_contrainte": false,
    "corection": false
  },
  {
    "id": 6,
    "value": "dropdown_list",
    "type_question": {
      "slug": "lineary_scale",
      "name": "Échelle linéaire"
    },
    "response_options": [],
    "is_mandatory": false,
    "response_redirection": false,
    "question_is_selected": "",

    "activate_vote": false,
    "constraint": "",
    "correction_explanation": "",
    "description": "",
    "placeholder": "",
    "poids": "",
    "with_validation_contrainte": false,
    "corection": false
  },
  {
    "id": 7,
    "value": "date",
    "type_question": {
      "name": "Date",
      "slug": "date"
    },
    "response_options": [],
    "is_mandatory": false,
    "response_redirection": false,
    "question_is_selected": "",

    "activate_vote": false,
    "constraint": "",
    "correction_explanation": "",
    "description": "",
    "placeholder": "",
    "poids": "",
    "with_validation_contrainte": false,
    "corection": false
  },
  {
    "id": 8,
    "value": "hour",
    "type_question": {
      "name": "Heure",
      "slug": "hour"
    },
    "corection": false
  },
  {
    "id": 9,
    "content": "",
    "poids": "images",
    "type": "texte"
  },
  {
    "id": 10,
    "content": "",
    "display": "full",
    "poids": "",
    "type": "image"
  },
  {
    "id": 11,
    "content": "",
    "urlYoutube": "",
    "poids": "",
    "type": "embed"
  },
  {
    "id": 12,
    "content": "",
    "urlYoutube": "",
    "poids": "",
    "type": "video"
  }
]
